{
	"title": "Summary",
	"plugins" : [
		"toggle-chapters",
		"github-buttons",
		"editlink",
		"copy-code-button",
		"page-footer-ex",
		"expandable-chapters-small",
		"prism", 
		"-highlight",
		"-lunr", 
		"-search", 
		"search-pro",
		"donate",
		"splitter",
		"disqus"
	],
	"pluginsConfig": {
		"editlink": {
			"base": "https://github.com/wangzhebufangqi/ActionTest",
			"label": "Edit This Page"
		},	
		"github-buttons": {
			"buttons": [{
				"user": "wangzhebufangqi",
				"repo": "ActionTest",
				"type": "star",
				"size": "small"
			}, {
				"user": "wangzhebufangqi",
				"type": "follow",
				"size": "small",
				"count": false
			}]	
		},	
		"page-footer-ex": {
            "copyright": "[mrcode](https://github.com/wangzhebufangqi)",
            "markdown": true,
            "update_label": "<i>updated</i>",
            "update_format": "YYYY-MM-DD HH:mm:ss"
		},	
		"prism": {
			"css": ["prismjs/themes/prism-solarizedlight.css"],
			"lang": {"flow": "typescript"}
		},	
		"donate": {
			"wechat": "https://gitee.com/wangzhebufangqi/PictureBed/raw/master/20201122131942.png",
			"alipay": "https://gitee.com/wangzhebufangqi/PictureBed/raw/master/20201122131820.png",
			"title": "",
			"button": "Donate",
			"alipayText": "支付宝捐赠",
			"wechatText": "微信捐赠"
		},
		"disqus": {
            "shortName": "wangzhebufangqi"
        }
	},
	"ignores" : ["_book", "node_modules"]
}	